{
    "headers": {
        "accept": "image/png",
        "content-type": "application/json"
    },
    "payload": {
        "evalscript": "\n      //VERSION=3\n\n        let viz = ColorGradientVisualizer.createBlueRed();\n\n        function evaluatePixel(samples) {\n          let val = index(samples.B08, samples.B04);\n          val = viz.process(val);\n          val.push(samples.dataMask);\n          return val;\n        }\n\n        function setup() {\n        return {\n          input: [{\n          bands: [\n            \"B04\",\n            \"B08\",\n            \"dataMask\"\n          ]\n          }],\n          output: {\n          bands: 4\n          }\n        }\n        }\n    ",
        "input": {
            "bounds": {
                "bbox": [
                    28.543146,
                    22.82078,
                    28.551235,
                    22.828175
                ],
                "geometry": {
                    "coordinates": [
                        [
                            [
                                28.54748,
                                22.828115
                            ],
                            [
                                28.54748,
                                22.828115
                            ],
                            [
                                28.547909,
                                22.828115
                            ],
                            [
                                28.547909,
                                22.828115
                            ],
                            [
                                28.548124,
                                22.828056
                            ],
                            [
                                28.548124,
                                22.828056
                            ],
                            [
                                28.548381,
                                22.827977
                            ],
                            [
                                28.548381,
                                22.827997
                            ],
                            [
                                28.548553,
                                22.827957
                            ],
                            [
                                28.548789,
                                22.827918
                            ],
                            [
                                28.548789,
                                22.827918
                            ],
                            [
                                28.549025,
                                22.827819
                            ],
                            [
                                28.549025,
                                22.827819
                            ],
                            [
                                28.549261,
                                22.82776
                            ],
                            [
                                28.549261,
                                22.82776
                            ],
                            [
                                28.549476,
                                22.827601
                            ],
                            [
                                28.549476,
                                22.827601
                            ],
                            [
                                28.549733,
                                22.827404
                            ],
                            [
                                28.549733,
                                22.827404
                            ],
                            [
                                28.549948,
                                22.827245
                            ],
                            [
                                28.549948,
                                22.827245
                            ],
                            [
                                28.550141,
                                22.827107
                            ],
                            [
                                28.550334,
                                22.826929
                            ],
                            [
                                28.550506,
                                22.82683
                            ],
                            [
                                28.550677,
                                22.826633
                            ],
                            [
                                28.550763,
                                22.826474
                            ],
                            [
                                28.550806,
                                22.826277
                            ],
                            [
                                28.550806,
                                22.826277
                            ],
                            [
                                28.550913,
                                22.826138
                            ],
                            [
                                28.550978,
                                22.82602
                            ],
                            [
                                28.551021,
                                22.825802
                            ],
                            [
                                28.551021,
                                22.825802
                            ],
                            [
                                28.551042,
                                22.825604
                            ],
                            [
                                28.551042,
                                22.825604
                            ],
                            [
                                28.551171,
                                22.825407
                            ],
                            [
                                28.551171,
                                22.825407
                            ],
                            [
                                28.551171,
                                22.825268
                            ],
                            [
                                28.551235,
                                22.82513
                            ],
                            [
                                28.551214,
                                22.824991
                            ],
                            [
                                28.551214,
                                22.824774
                            ],
                            [
                                28.551214,
                                22.824774
                            ],
                            [
                                28.551214,
                                22.824655
                            ],
                            [
                                28.551214,
                                22.824359
                            ],
                            [
                                28.551214,
                                22.824359
                            ],
                            [
                                28.551214,
                                22.82426
                            ],
                            [
                                28.551214,
                                22.824042
                            ],
                            [
                                28.551214,
                                22.824042
                            ],
                            [
                                28.551214,
                                22.823924
                            ],
                            [
                                28.551171,
                                22.823647
                            ],
                            [
                                28.551171,
                                22.823647
                            ],
                            [
                                28.551128,
                                22.823489
                            ],
                            [
                                28.551085,
                                22.823331
                            ],
                            [
                                28.551021,
                                22.823153
                            ],
                            [
                                28.550956,
                                22.823054
                            ],
                            [
                                28.550913,
                                22.822817
                            ],
                            [
                                28.550913,
                                22.822817
                            ],
                            [
                                28.550849,
                                22.822718
                            ],
                            [
                                28.550763,
                                22.82254
                            ],
                            [
                                28.550634,
                                22.822382
                            ],
                            [
                                28.550613,
                                22.822342
                            ],
                            [
                                28.550506,
                                22.822223
                            ],
                            [
                                28.550441,
                                22.822144
                            ],
                            [
                                28.550313,
                                22.821966
                            ],
                            [
                                28.550248,
                                22.821867
                            ],
                            [
                                28.550227,
                                22.821867
                            ],
                            [
                                28.550098,
                                22.821729
                            ],
                            [
                                28.550076,
                                22.82167
                            ],
                            [
                                28.549883,
                                22.821551
                            ],
                            [
                                28.549712,
                                22.821512
                            ],
                            [
                                28.549626,
                                22.821472
                            ],
                            [
                                28.549476,
                                22.821334
                            ],
                            [
                                28.549433,
                                22.821274
                            ],
                            [
                                28.549218,
                                22.821195
                            ],
                            [
                                28.549218,
                                22.821195
                            ],
                            [
                                28.549004,
                                22.821116
                            ],
                            [
                                28.548875,
                                22.821057
                            ],
                            [
                                28.548703,
                                22.821057
                            ],
                            [
                                28.548596,
                                22.820997
                            ],
                            [
                                28.548489,
                                22.820958
                            ],
                            [
                                28.548317,
                                22.82082
                            ],
                            [
                                28.548167,
                                22.820859
                            ],
                            [
                                28.547974,
                                22.820839
                            ],
                            [
                                28.547845,
                                22.820839
                            ],
                            [
                                28.547695,
                                22.820859
                            ],
                            [
                                28.547394,
                                22.82078
                            ],
                            [
                                28.547394,
                                22.82078
                            ],
                            [
                                28.547266,
                                22.82078
                            ],
                            [
                                28.547072,
                                22.82078
                            ],
                            [
                                28.546858,
                                22.820839
                            ],
                            [
                                28.546643,
                                22.820879
                            ],
                            [
                                28.546643,
                                22.820879
                            ],
                            [
                                28.546493,
                                22.820879
                            ],
                            [
                                28.54615,
                                22.820978
                            ],
                            [
                                28.54615,
                                22.820978
                            ],
                            [
                                28.546021,
                                22.820997
                            ],
                            [
                                28.545785,
                                22.821096
                            ],
                            [
                                28.545785,
                                22.821096
                            ],
                            [
                                28.545613,
                                22.821116
                            ],
                            [
                                28.545399,
                                22.821175
                            ],
                            [
                                28.54527,
                                22.821235
                            ],
                            [
                                28.54512,
                                22.821314
                            ],
                            [
                                28.544948,
                                22.821452
                            ],
                            [
                                28.544755,
                                22.821531
                            ],
                            [
                                28.544605,
                                22.821591
                            ],
                            [
                                28.544433,
                                22.821769
                            ],
                            [
                                28.544283,
                                22.821907
                            ],
                            [
                                28.544154,
                                22.822144
                            ],
                            [
                                28.544154,
                                22.822144
                            ],
                            [
                                28.54409,
                                22.822184
                            ],
                            [
                                28.543897,
                                22.822283
                            ],
                            [
                                28.543811,
                                22.822421
                            ],
                            [
                                28.543768,
                                22.822639
                            ],
                            [
                                28.543768,
                                22.822639
                            ],
                            [
                                28.543639,
                                22.822777
                            ],
                            [
                                28.543596,
                                22.822955
                            ],
                            [
                                28.54351,
                                22.823054
                            ],
                            [
                                28.543489,
                                22.823133
                            ],
                            [
                                28.543425,
                                22.82335
                            ],
                            [
                                28.543425,
                                22.82335
                            ],
                            [
                                28.54336,
                                22.823528
                            ],
                            [
                                28.543231,
                                22.823766
                            ],
                            [
                                28.543231,
                                22.823766
                            ],
                            [
                                28.54321,
                                22.823904
                            ],
                            [
                                28.54321,
                                22.824003
                            ],
                            [
                                28.54321,
                                22.82424
                            ],
                            [
                                28.54321,
                                22.82424
                            ],
                            [
                                28.543146,
                                22.824596
                            ],
                            [
                                28.543146,
                                22.824596
                            ],
                            [
                                28.543167,
                                22.824853
                            ],
                            [
                                28.543167,
                                22.824853
                            ],
                            [
                                28.543253,
                                22.825031
                            ],
                            [
                                28.543382,
                                22.825268
                            ],
                            [
                                28.543382,
                                22.825268
                            ],
                            [
                                28.543382,
                                22.825525
                            ],
                            [
                                28.543382,
                                22.825525
                            ],
                            [
                                28.543403,
                                22.825664
                            ],
                            [
                                28.543489,
                                22.825881
                            ],
                            [
                                28.543489,
                                22.825881
                            ],
                            [
                                28.543639,
                                22.826059
                            ],
                            [
                                28.543725,
                                22.826296
                            ],
                            [
                                28.543725,
                                22.826296
                            ],
                            [
                                28.543897,
                                22.826534
                            ],
                            [
                                28.543897,
                                22.826534
                            ],
                            [
                                28.544025,
                                22.826692
                            ],
                            [
                                28.54424,
                                22.82689
                            ],
                            [
                                28.54424,
                                22.82689
                            ],
                            [
                                28.544369,
                                22.827068
                            ],
                            [
                                28.544476,
                                22.827186
                            ],
                            [
                                28.544712,
                                22.827344
                            ],
                            [
                                28.544712,
                                22.827344
                            ],
                            [
                                28.544927,
                                22.827483
                            ],
                            [
                                28.544927,
                                22.827483
                            ],
                            [
                                28.54512,
                                22.827582
                            ],
                            [
                                28.545334,
                                22.82772
                            ],
                            [
                                28.545334,
                                22.82772
                            ],
                            [
                                28.545442,
                                22.82772
                            ],
                            [
                                28.545613,
                                22.827799
                            ],
                            [
                                28.545785,
                                22.827878
                            ],
                            [
                                28.545957,
                                22.827977
                            ],
                            [
                                28.546214,
                                22.827997
                            ],
                            [
                                28.546214,
                                22.827997
                            ],
                            [
                                28.546429,
                                22.827997
                            ],
                            [
                                28.546429,
                                22.827997
                            ],
                            [
                                28.546643,
                                22.828115
                            ],
                            [
                                28.546643,
                                22.828115
                            ],
                            [
                                28.546858,
                                22.828135
                            ],
                            [
                                28.546858,
                                22.828135
                            ],
                            [
                                28.546965,
                                22.828155
                            ],
                            [
                                28.547051,
                                22.828175
                            ],
                            [
                                28.547158,
                                22.828175
                            ],
                            [
                                28.54748,
                                22.828115
                            ]
                        ]
                    ],
                    "type": "Polygon"
                },
                "properties": {
                    "crs": "http://www.opengis.net/def/crs/EPSG/0/4326"
                }
            },
            "data": [
                {
                    "dataFilter": {
                        "timeRange": {
                            "from": "2024-03-18T00:00:00Z",
                            "to": "2024-03-18T23:59:59Z"
                        }
                    },
                    "type": "sentinel-2-l2a"
                }
            ]
        },
        "output": {
            "height": 512,
            "responses": [
                {
                    "format": {
                        "type": "image/png"
                    },
                    "identifier": "default"
                }
            ],
            "width": 512
        }
    },
    "timestamp": "2024-06-03T09:53:36.671446",
    "url": "https://services.sentinel-hub.com/api/v1/process"
}